gplaycli2/__init__.py
gplaycli2/__main__.py
gplaycli2/gplaycli.py
gplaycli2/hooks.py
gplaycli2/util.py
gplaycli2-3.30.data/data/etc/gplaycli/gplaycli.conf
gplaycli2-3.30.dist-info/LICENSE.md
gplaycli2-3.30.dist-info/METADATA
gplaycli2-3.30.dist-info/WHEEL
gplaycli2-3.30.dist-info/entry_points.txt
gplaycli2-3.30.dist-info/top_level.txt
gplaycli2-3.30.dist-info/RECORD
