Metadata-Version: 2.1
Name: gplaycli2
Version: 3.30
Summary: GPlayCli2, a Google play downloader command line interface
Home-page: https://github.com/besendorf/gplaycli
Author: besendorf
Author-email: janik@besendorf.org
License: AGPLv3
Platform: UNKNOWN
License-File: LICENSE.md
Requires-Dist: gpapi2 (>=0.4.4.4)
Requires-Dist: pyaxmlparser
